sd4py/SD4Py.java
sd4py/SD4PyOntologyCreator.java
sd4py/__init__.py
sd4py/sd4py.jar
sd4py/sd4py.py
sd4py/sd4py_extra.py
sd4py/vikamine_kernel.jar
SD4Py-0.1.7.dist-info/METADATA
SD4Py-0.1.7.dist-info/WHEEL
SD4Py-0.1.7.dist-info/top_level.txt
SD4Py-0.1.7.dist-info/RECORD
