Metadata-Version: 2.1
Name: SD4Py
Version: 0.1.7
Summary: Subgroup discovery and visualisation for python based on the VIKAMINE kernel
Author: Dan Hudson
Author-email: daniel.dominic.hudson@uni-osnabrueck.de
License: Licence.txt
Classifier: License :: OSI Approved :: GNU Library or Lesser General Public License (LGPL)
Classifier: Programming Language :: Python :: 3
Requires-Dist: JPype1
Requires-Dist: numpy
Requires-Dist: pandas
Requires-Dist: matplotlib
Requires-Dist: seaborn
Requires-Dist: networkx
